cli/test_decrypt_password.py
cli/test_generate_key.py
cli/test_generate_openapi_schema.py
cli/test_generate_password.py
cli/test_generate_route_manifest_cli.py
cli/test_repost_failed_calls.py
client/test_analyser.py
client/test_context.py
client/test_destinations.py
client/test_rsync.py
client/test_watchdir.py
client/contexts/test_atlas.py
client/contexts/test_tomo.py
instrument_server/__init__.py
instrument_server/test_api.py
instrument_server/test_init.py
murfey/__init__.py
murfey/bootstrap/__main__.py
murfey/cli/__init__.py
murfey/cli/add_user.py
murfey/cli/create_db.py
murfey/cli/db_sessions.py
murfey/cli/decrypt_db_password.py
murfey/cli/dummy.py
murfey/cli/generate_crypto_key.py
murfey/cli/generate_db_password.py
murfey/cli/generate_openapi_schema.py
murfey/cli/generate_route_manifest.py
murfey/cli/inject_spa_processing.py
murfey/cli/repost_failed_calls.py
murfey/client/__init__.py
murfey/client/analyser.py
murfey/client/context.py
murfey/client/destinations.py
murfey/client/gain_ref.py
murfey/client/instance_environment.py
murfey/client/multigrid_control.py
murfey/client/rsync.py
murfey/client/update.py
murfey/client/watchdir.py
murfey/client/watchdir_multigrid.py
murfey/client/contexts/__init__.py
murfey/client/contexts/atlas.py
murfey/client/contexts/clem.py
murfey/client/contexts/fib.py
murfey/client/contexts/spa.py
murfey/client/contexts/spa_metadata.py
murfey/client/contexts/tomo.py
murfey/client/contexts/tomo_metadata.py
murfey/instrument_server/__init__.py
murfey/instrument_server/api.py
murfey/instrument_server/main.py
murfey/server/__init__.py
murfey/server/feedback.py
murfey/server/gain.py
murfey/server/ispyb.py
murfey/server/main.py
murfey/server/murfey_db.py
murfey/server/prometheus.py
murfey/server/run.py
murfey/server/api/__init__.py
murfey/server/api/auth.py
murfey/server/api/bootstrap.py
murfey/server/api/clem.py
murfey/server/api/display.py
murfey/server/api/file_io_frontend.py
murfey/server/api/file_io_instrument.py
murfey-0.23.1.dist-info/licenses/AUTHORS.rst
murfey-0.23.1.dist-info/licenses/LICENSE
murfey-0.23.1.dist-info/METADATA
murfey-0.23.1.dist-info/WHEEL
murfey-0.23.1.dist-info/entry_points.txt
murfey-0.23.1.dist-info/top_level.txt
murfey-0.23.1.dist-info/RECORD
