Metadata-Version: 2.4
Name: murfey
Version: 0.23.1
Summary: Client-Server architecture hauling Cryo-EM data
License: Copyright (c) 2022 Diamond Light Source.
Project-URL: Bug-Tracker, https://github.com/DiamondLightSource/python-murfey/issues
Project-URL: Documentation, https://github.com/DiamondLightSource/python-murfey
Project-URL: GitHub, https://github.com/DiamondLightSource/python-murfey
Classifier: Development Status :: 3 - Alpha
Classifier: Environment :: Console
Classifier: Intended Audience :: Science/Research
Classifier: License :: OSI Approved :: BSD License
Classifier: Operating System :: OS Independent
Classifier: Programming Language :: Python :: 3 :: Only
Classifier: Programming Language :: Python :: 3.10
Classifier: Programming Language :: Python :: 3.11
Classifier: Programming Language :: Python :: 3.12
Requires-Python: >=3.10
License-File: LICENSE
License-File: AUTHORS.rst
Requires-Dist: aiohttp
Requires-Dist: defusedxml
Requires-Dist: fastapi[standard-no-fastapi-cloud-cli]>=0.116.0
Requires-Dist: pydantic>=2
Requires-Dist: pydantic-settings
Requires-Dist: python-jose
Requires-Dist: requests
Requires-Dist: rich
Requires-Dist: werkzeug
Requires-Dist: xmltodict
Provides-Extra: cicd
Requires-Dist: pytest-cov; extra == "cicd"
Provides-Extra: developer
Requires-Dist: bump-my-version; extra == "developer"
Requires-Dist: ipykernel; extra == "developer"
Requires-Dist: pre-commit; extra == "developer"
Requires-Dist: pytest; extra == "developer"
Requires-Dist: pytest-asyncio; extra == "developer"
Requires-Dist: pytest-mock; extra == "developer"
Provides-Extra: server
Requires-Dist: cryptography; extra == "server"
Requires-Dist: graypy; extra == "server"
Requires-Dist: ispyb>=10.2.4; extra == "server"
Requires-Dist: jinja2; extra == "server"
Requires-Dist: mrcfile; extra == "server"
Requires-Dist: numpy<2; extra == "server"
Requires-Dist: packaging; extra == "server"
Requires-Dist: passlib; extra == "server"
Requires-Dist: pillow; extra == "server"
Requires-Dist: prometheus_client; extra == "server"
Requires-Dist: sqlalchemy[postgresql]; extra == "server"
Requires-Dist: sqlmodel; extra == "server"
Requires-Dist: stomp-py>8.1.1; extra == "server"
Requires-Dist: zocalo>=1; extra == "server"
Dynamic: license-file
